Workbook

Sheet Apresentação

Sheet Dados Brutos
A1: temporada | B1: tipo_mov | C1: nome_jogador | D1: posição | E1: nacionalidade | F1: clube | G1: valor_transferencia | H1: idade | I1: tipo_negociacao
A2: 2019/20 | B2: entrada | C2: Tanguy Ndombele | D2: meio campo | E2: França | F2: Lyon | G2: 62000000 | H2: 22 | I2: Compra
A3: 2019-20 | B3: Entrada | C3: Steven Bergwijn | D3: PONTA | E3: holanda | F3: PSV Eindhoven | G3: €30M | H3: 22 | I3: compra
A4: 2019/20 | B4: saida | C4: Christian Eriksen | D4: Meia | E4: Dinamarca | F4: Inter de Milão | G4: 27 milhões | H4: 27 | I4: Venda
A5: 2020/21 | B5: Entrada | C5: Pierre Emile Højbjerg | D5: volante | E5: dinamarca | F5: Southampton | G5: 16.6m | H5: 25 | I5: COMPRA
A6: 2020_21 | B6: entrada | C6: Sergio Reguilón | D6: Lateral-esquerdo | E6: Espanha | F6: Real Madrid | G6: 30000000 | H6: 23 anos | I6: Compra
A7: 2020/21 | B7: Saída | C7: Jan Vertonghen | D7: ZAG | E7: Bélgica | F7: Benfica | G7: Livre | H7: 33 | I7: fim contrato
A8: 2021/22 | B8: Entrada | C8: Cristian Romero | D8: zagueiro | E8: argentina | F8: Atalanta | G8: 52M EUR | H8: 23 | I8: Compra
A9: 2021-22 | B9: entrada | C9: Dejan Kulusevski | D9: Ponta direita | E9: Suécia | F9: Juventus | G9: loan | H9: 21 | I9: emprestimo
A10: 2021/22 | B10: Saida | C10: Toby Alderweireld | D10: Defensor | E10: Belgica | F10: Al Duhail | G10: 13.000.000 | H10: 32 | I10: VENDA
A11: 2022/23 | B11: Entrada | C11: Richarlison | D11: Atacante | E11: Brasil | F11: Everton | G11: 58 mi | H11: 25 | I11: Compra
A12: 2022/2023 | B12: Entrada | C12: Yves Bissouma | D12: VOL | E12: Mali | F12: Brighton | G12: €29.000.000 | H12: 25 | I12: Compra
A13: 2022/23 | B13: saida | C13: Steven Bergwijn | D13: winger | E13: Holanda | F13: Ajax | G13: 31,3M | H13: 24 | I13: Venda
A14: 2023/24 | B14: ENTRADA | C14: James Maddison | D14: meio-campo | E14: Inglaterra | F14: Leicester City | G14: 46300000 | H14: 26 | I14: compra
A15: 2023/24 | B15: Entrada | C15: Micky van de Ven | D15: zagueiro | E15: Holanda | F15: Wolfsburg | G15: 40M | H15: 22 | I15: Compra
A16: 2023/24 | B16: Saída | C16: Harry Kane | D16: Centroavante | E16: Inglaterra | F16: Bayern | G16: 95000000 | H16: 30 | I16: VENDA
A17: 2024/25 | B17: entrada | C17: Dominic Solanke | D17: ATA | E17: Inglaterra | F17: Bournemouth | G17: 65 milhões | H17: 26 | I17: Compra
A18: 2024/25 | B18: Entrada | C18: Archie Gray | D18: Meio Campo | E18: inglaterra | F18: Leeds United | G18: 41m | H18: 18 | I18: Compra
A19: 2024/25 | B19: Saída | C19: Pierre-Emile Hojbjerg | D19: volante | E19: Dinamarca | F19: Marseille | G19: 13.5M | H19: 29 | I19: Venda
A20: 2023/24 | B20: Saída | C20: Harry Kane | D20: Centroavante | E20: Inglaterra | F20: Bayern | G20: 95000000 | H20: 30 | I20: VENDA
A21: 2022/23 | C21: Ivan Perisic | E21: Croácia | F21: Inter | H21: 33 | I21: Livre
A22: 2021/22 | B22: Entrda | C22: Rodrigo Bentancur | D22: meiocampo | E22: Uruguai | F22: Juventus | G22: 19000000 | H22: 24 | I22: Compra
A23: Compra | B23: 2020/21 | C23: Matt Doherty | D23: Irlanda | E23: Lateral | F23: Wolves | G23: 16.8M | H23: 28 | I23: Entrada
A24: temporada | B24: tipo_mov | C24: nome_jogador | D24: posição | E24: nacionalidade | F24: clube | G24: valor_transferencia | H24: idade | I24: tipo_negociacao
A25: 2023/24 | B25: Entrada | C25: Brennan Johnson | D25: Ponta | E25: País de Gales | F25: Nottingham Forest | H25: 22 | I25: Compra

Sheet Dados Tratados
A1: Qualitativa Ordinal | B1: Qualitativa Nominal | C1: Qualitativa Nominal | D1: Qualitativa Nominal | E1: Qualitativa Nominal | F1: Qualitativa Nominal | G1: Quantitativa Contínua | H1: Quantitativa Discreta | I1: Qualitativa Ordinal | J1: Qualitativa Nominal
A2: temporada | B2: tipo_movimentação | C2: nome_jogador | D2: posição | E2: nacionalidade | F2: clube | G2: valor_transferência | H2: idade | I2: faixa_etária | J2: tipo_negociação
A3: 2019/20 | B3: Entrada | C3: Tanguy Ndombélé | D3: Meio-campista | E3: França | F3: Lyon | G3: 62000000 | H3: 22 | I3: =IF(H3<=20,"Muito Jovem (16-20 anos)",IF(AND(H3>=21,H3<=25),"Jovem (21-25 anos)",IF(AND(H3>=26,H3<=30),"Experiente (26-30 anos)",IF(H3>31,"Veterano (31+ anos)")))) -> Jovem (21-25 anos) | J3: Compra
A4: 2019/20 | B4: Entrada | C4: Steven Bergwijn | D4: Atacante | E4: Holanda | F4: PSV Eindhoven | G4: 30000000 | H4: 22 | I4: =IF(H4<=20,"Muito Jovem (16-20 anos)",IF(AND(H4>=21,H4<=25),"Jovem (21-25 anos)",IF(AND(H4>=26,H4<=30),"Experiente (26-30 anos)",IF(H4>31,"Veterano (31+ anos)")))) -> Jovem (21-25 anos) | J4: Compra
A5: 2019/20 | B5: Saída | C5: Christian Eriksen | D5: Meio-campista | E5: Dinamarca | F5: Inter Milan | G5: 27000000 | H5: 27 | I5: =IF(H5<=20,"Muito Jovem (16-20 anos)",IF(AND(H5>=21,H5<=25),"Jovem (21-25 anos)",IF(AND(H5>=26,H5<=30),"Experiente (26-30 anos)",IF(H5>31,"Veterano (31+ anos)")))) -> Experiente (26-30 anos) | J5: Venda
A6: 2020/21 | B6: Entrada | C6: Pierre-Emile Højbjerg | D6: Meio-campista | E6: Dinamarca | F6: Southampton | G6: 16600000 | H6: 25 | I6: =IF(H6<=20,"Muito Jovem (16-20 anos)",IF(AND(H6>=21,H6<=25),"Jovem (21-25 anos)",IF(AND(H6>=26,H6<=30),"Experiente (26-30 anos)",IF(H6>31,"Veterano (31+ anos)")))) -> Jovem (21-25 anos) | J6: Compra
A7: 2020/21 | B7: Entrada | C7: Sergio Reguilón | D7: Defensor | E7: Espanha | F7: Real Madrid | G7: 30000000 | H7: 23 | I7: =IF(H7<=20,"Muito Jovem (16-20 anos)",IF(AND(H7>=21,H7<=25),"Jovem (21-25 anos)",IF(AND(H7>=26,H7<=30),"Experiente (26-30 anos)",IF(H7>31,"Veterano (31+ anos)")))) -> Jovem (21-25 anos) | J7: Compra
A8: 2020/21 | B8: Saída | C8: Jan Vertonghen | D8: Defensor | E8: Bélgica | F8: Benfica | G8: 0 | H8: 33 | I8: =IF(H8<=20,"Muito Jovem (16-20 anos)",IF(AND(H8>=21,H8<=25),"Jovem (21-25 anos)",IF(AND(H8>=26,H8<=30),"Experiente (26-30 anos)",IF(H8>31,"Veterano (31+ anos)")))) -> Veterano (31+ anos) | J8: Livre
A9: 2020/21 | B9: Entrada | C9: Matt Doherty | D9: Defensor | E9: Irlanda | F9: Wolves | G9: 16800000 | H9: 28 | I9: =IF(H9<=20,"Muito Jovem (16-20 anos)",IF(AND(H9>=21,H9<=25),"Jovem (21-25 anos)",IF(AND(H9>=26,H9<=30),"Experiente (26-30 anos)",IF(H9>31,"Veterano (31+ anos)")))) -> Experiente (26-30 anos) | J9: Compra
A10: 2021/22 | B10: Entrada | C10: Cristian Romero | D10: Defensor | E10: Argentina | F10: Atalanta | G10: 52000000 | H10: 23 | I10: =IF(H10<=20,"Muito Jovem (16-20 anos)",IF(AND(H10>=21,H10<=25),"Jovem (21-25 anos)",IF(AND(H10>=26,H10<=30),"Experiente (26-30 anos)",IF(H10>31,"Veterano (31+ anos)")))) -> Jovem (21-25 anos) | J10: Compra
A11: 2021/22 | B11: Entrada | C11: Dejan Kulusevski | D11: Atacante | E11: Suécia | F11: Juventus | G11: 0 | H11: 21 | I11: =IF(H11<=20,"Muito Jovem (16-20 anos)",IF(AND(H11>=21,H11<=25),"Jovem (21-25 anos)",IF(AND(H11>=26,H11<=30),"Experiente (26-30 anos)",IF(H11>31,"Veterano (31+ anos)")))) -> Jovem (21-25 anos) | J11: Empréstimo
A12: 2021/22 | B12: Saída | C12: Toby Alderweireld | D12: Defensor | E12: Bélgica | F12: Al Duhail | G12: 13000000 | H12: 32 | I12: =IF(H12<=20,"Muito Jovem (16-20 anos)",IF(AND(H12>=21,H12<=25),"Jovem (21-25 anos)",IF(AND(H12>=26,H12<=30),"Experiente (26-30 anos)",IF(H12>31,"Veterano (31+ anos)")))) -> Veterano (31+ anos) | J12: Venda
A13: 2021/22 | B13: Entrada | C13: Rodrigo Bentancur | D13: Meio-campista | E13: Uruguai | F13: Juventus | G13: 19000000 | H13: 24 | I13: =IF(H13<=20,"Muito Jovem (16-20 anos)",IF(AND(H13>=21,H13<=25),"Jovem (21-25 anos)",IF(AND(H13>=26,H13<=30),"Experiente (26-30 anos)",IF(H13>31,"Veterano (31+ anos)")))) -> Jovem (21-25 anos) | J13: Compra
A14: 2022/23 | B14: Entrada | C14: Richarlison | D14: Atacante | E14: Brasil | F14: Everton | G14: 58000000 | H14: 25 | I14: =IF(H14<=20,"Muito Jovem (16-20 anos)",IF(AND(H14>=21,H14<=25),"Jovem (21-25 anos)",IF(AND(H14>=26,H14<=30),"Experiente (26-30 anos)",IF(H14>31,"Veterano (31+ anos)")))) -> Jovem (21-25 anos) | J14: Compra
... A24: 2024/25 | B24: Saída | C24: Pierre-Emile Højbjerg | D24: Meio-campista | E24: Dinamarca | F24: Olympique Marseille | G24: 13500000 | H24: 29 | I24: =IF(H24<=20,"Muito Jovem (16-20 anos)",IF(AND(H24>=21,H24<=25),"Jovem (21-25 anos)",IF(AND(H24>=26,H24<=30),"Experiente (26-30 anos)",IF(H24>31,"Veterano (31+ anos)")))) -> Experiente (26-30 anos) | J24: Venda

Sheet Análises
C4: Total de Transferências | D4: Total de Entradas | E4: Total de Saídas | F4: Total de Jogadores | G4: Total de Nacionalidades | H4: Idade Média dos Jogadores | I4: Saídas/Vendas de Jogadores em %
C5: =COUNTA('Dados Tratados'!A3:A24) -> 22 | D5: =COUNTIF('Dados Tratados'!B:B, "Entrada") -> 16 | E5: =COUNTIF('Dados Tratados'!B:B, "Saída") -> 6 | F5: =COUNTA(_xlfn.UNIQUE('Dados Tratados'!C3:C24, ,)) -> 20 | G5: =COUNTA(_xlfn.UNIQUE('Dados Tratados'!E3:E24, ,)) -> 14 | H5: =AVERAGE('Dados Tratados'!H3:H24) -> 25.454545 | I5: =(C22/D22)*100 -> 24.529332
A14: Somas de Entradas e Saídas | O14: Soma do Valor das Transferências | P14: Tipo de Movimentação | Y14: Contagem de Jogadores | Z14: Tipo de Movimentação | AK14: Contagem de Nacionalidades | AL14: Contagem de Jogadores | AN14: Clubes | AO14: Contagem de Jogadores | BB14: Tipo de Movimentação | BE14: Posições | BF14: Porcentagem (%) do Total
A15: Temporadas | B15: Entrada | C15: Saída | D15: Total Geral | F15: Temporadas | G15: Saldo por Temporada | O15: Posições | P15: Entrada | R15: Posições | S15: Porcentagem (%) do Total | Y15: Faixa Etária | Z15: Entrada | AB15: Faixa Etária | AC15: Porcentagem (% do Total) | AK15: Nacionalidades | AL15: Entrada | AN15: Origem das Contratações | AO15: Entrada | BB15: Saída | BE15: Atacante | BF15: 0.702
A16: 2019/20 | B16: 92000000 | C16: 27000000 | D16: 119000000 | F16: 2019/20 | G16: =C16-B16 -> -65000000 | O16: Meio-campista | P16: 213900000 | R16: Meio-campista | S16: =P16/$P$19 -> 0.38665944 | Y16: Muito Jovem (16-20 anos) | Z16: 1 | AB16: Muito Jovem (16-20 anos) | AC16: =Z16/$Z$20 -> 0.0625 | AK16: França | AL16: 1 | AN16: Atalanta | AO16: 1 | BA16: Posições e Jogadores | BB16: Soma do Valores | BC16: Porcentagem (%) do Total | BE16: Meio-campista | BF16: 0.225 | BL16: Investimento no Período | BN16: Retorno no Período | BP16: Saldo Total no Período
A17: 2020/21 | B17: 63400000 | C17: 0 | D17: 63400000 | F17: 2020/21 | G17: =C17-B17 -> -63400000 | O17: Atacante | P17: 200500000 | R17: Atacante | S17: =P17/$P$19 -> 0.36243673 | Y17: Veterano (31+ anos) | Z17: 1 | AB17: Veterano (31+ anos) | AC17: =Z17/$Z$20 -> 0.0625 | AK17: Uruguai | AL17: 1 | AN17: Argentina | AO17: 1 | BA17: Atacante | BB17: 126300000 | BC17: 0.70244716 | BE17: Defensor | BF17: 0.072 | BL17: 553200000 | BN17: 179800000 | BP17: -373400000
A18: 2021/22 | B18: 71000000 | C18: 13000000 | D18: 84000000 | F18: 2021/22 | G18: =C18-B18 -> -58000000 | O18: Defensor | P18: 138800000 | R18: Defensor | S18: =P18/$P$19 -> 0.25090383 | Y18: Experiente (26-30 anos) | Z18: 3 | AB18: Experiente (26-30 anos) | AC18: =Z18/$Z$20 -> 0.1875 | AK18: Argentina | AL18: 1 | AN18: Bournemouth | AO18: 1 | BA18: Harry Kane | BB18: 95000000 | BC18: 0.52836485 | BE18: Total Geral | BF18: 1
A19: 2022/23 | B19: 87000000 | C19: 31300000 | D19: 118300000 | F19: 2022/23 | G19: =C19-B19 -> -55700000 | O19: Total Geral | P19: 553200000 | R19: Total Geral | S19: =P19/$P$19 -> 1 | Y19: Jovem (21-25 anos) | Z19: 11 | AB19: Jovem (21-25 anos) | AC19: =Z19/$Z$20 -> 0.6875 | AK19: Croácia | AL19: 1 | AN19: Inglaterra | AO19: 1 | BA19: Steven Bergwijn | BB19: 31300000 | BC19: 0.17408231
A20: 2023/24 | B20: 133800000 | C20: 95000000 | D20: 228800000 | F20: 2023/24 | G20: =C20-B20 -> -38800000 | Y20: Total Geral | Z20: 16 | AB20: Total Geral | AC20: =Z20/$Z$20 -> 1 | AK20: Irlanda | AL20: 1 | AN20: Brighton | AO20: 1 | BA20: Meio-campista | BB20: 40500000 | BC20: 0.22525028 | BL20: Inv. em Meio-campistas | BN20: Inv. em Atacantes | BP20: Inv. em Defensores
A21: 2024/25 | B21: 106000000 | C21: 13500000 | D21: 119500000 | F21: 2024/25 | G21: =C21-B21 -> -92500000 | AK21: Espanha | AL21: 1 | AN21: Mali | AO21: 1 | BA21: Christian Eriksen | BB21: 27000000 | BC21: 0.15016685 | BL21: 0.38665944 | BN21: 0.36243673 | BP21: 0.25090383
A22: Total Geral | B22: 553200000 | C22: 179800000 | D22: 733000000 | F22: Total Geral | G22: =C22-B22 -> -373400000 | AK22: Mali | AL22: 1 | AN22: Everton | AO22: 1 | BA22: Pierre-Emile Højbjerg | BB22: 13500000 | BC22: 0.075083426
AK23: Dinamarca | AL23: 1 | AN23: Brasil | AO23: 1 | BA23: Defensor | BB23: 13000000 | BC23: 0.072302558
AK24: País De Gales | AL24: 1 | AN24: Inter Milan | AO24: 1 | BA24: Toby Alderweireld | BB24: 13000000 | BC24: 0.072302558 | BL24: Cont. de Jovens | BN24: Cont. de Experientes | BP24: Cont. de Veteranos
AK25: Brasil | AL25: 1 | AN25: Croácia | AO25: 1 | BA25: Jan Vertonghen | BB25: 0 | BC25: 0 | BL25: 0.6875 | BN25: 0.1875 | BP25: 0.0625
AK26: Suécia | AL26: 1 | AN26: Juventus | AO26: 2 | BA26: Total Geral | BB26: 179800000 | BC26: 1
AK27: Holanda | AL27: 2 | AN27: Suécia | AO27: 1
AK28: Inglaterra | AL28: 3 | AN28: Uruguai | AO28: 1 | BL28: Jogadores Ingleses | BN28: Jogadores Holandeses | BP28: Nacionalidades Diversas
AK29: Total Geral | AL29: 16 | AN29: Leeds United | AO29: 1 | BL29: 3 | BN29: 2 | BP29: 13
AN30: Inglaterra | AO30: 1
AN31: Leicester City | AO31: 1
AN32: Inglaterra | AO32: 1 | BL32: Ret. de Atacantes | BN32: Ret. de Meio-campistas | BP32: Ret. de Defensores
AN33: Lyon | AO33: 1 | BL33: 0.702 | BN33: 0.225 | BP33: 0.072
AN34: França | AO34: 1
AN35: Nottingham Forest | AO35: 1
AN36: País De Gales | AO36: 1
AN37: PSV Eindhoven | AO37: 1
AN38: Holanda | AO38: 1
AN39: Real Madrid | AO39: 1
AN40: Espanha | AO40: 1
AN41: Southampton | AO41: 1
AN42: Dinamarca | AO42: 1
AN43: Wolfsburg | AO43: 1
AN44: Holanda | AO44: 1
AN45: Wolves | AO45: 1
... AN47: Total Geral | AO47: 16

Sheet Anotações
F103: Posições e Jogadores | G103: Soma do Valores
F104: Toby Alderweireld | G104: 13000000
F105: Pierre-Emile Højbjerg | G105: 13500000
F106: Christian Eriksen | G106: 27000000
F107: Steven Bergwijn | G107: 31300000
F108: Harry Kane | G108: 95000000
